diff3d.py
diff3d-0.3.0.dist-info/METADATA
diff3d-0.3.0.dist-info/WHEEL
diff3d-0.3.0.dist-info/entry_points.txt
diff3d-0.3.0.dist-info/licenses/LICENSE
diff3d-0.3.0.dist-info/RECORD
