Metadata-Version: 2.4
Name: diff3d
Version: 0.3.0
Summary: Fast visual 3d diff for STL, OBJ, 3MF, and STEP files
Project-URL: Homepage, https://github.com/bdlucas1/diff3d
Project-URL: Issues, https://github.com/bdlucas1/diff3d/issues
Project-URL: Discussions, https://github.com/bdlucas1/diff3d/discussions
Author: Bruce D. Lucas
License-File: LICENSE
Classifier: License :: OSI Approved :: MIT License
Classifier: Operating System :: OS Independent
Classifier: Programming Language :: Python :: 3
Requires-Python: >=3.9
Requires-Dist: lib3mf
Requires-Dist: msvc-runtime; platform_system == 'Windows'
Requires-Dist: numpy
Requires-Dist: pyvista
Requires-Dist: scipy
